{
  "project_info": {
    "project_number": "54702810896",
    "project_id": "sankadiokro-manager",
    "storage_bucket": "sankadiokro-manager.firebasestorage.app"
  },
  "client": [
    {
      "client_info": {
        "mobilesdk_app_id": "1:54702810896:android:5072a1135ac7c67c7e6795",
        "android_client_info": {
          "package_name": "com.sankadiokro.manager"
        }
      },
      "oauth_client": [
        {
          "client_id": "54702810896-p7vine9l71sr6uohj59kp7h31qaqtn6e.apps.googleusercontent.com",
          "client_type": 3
        }
      ],
      "api_key": [
        {
          "current_key": "AIzaSyBn6uvarIeS37QdtW8ERBHoHBaehIjcU6U"
        }
      ],
      "services": {
        "appinvite_service": {
          "other_platform_oauth_client": [
            {
              "client_id": "54702810896-p7vine9l71sr6uohj59kp7h31qaqtn6e.apps.googleusercontent.com",
              "client_type": 3
            }
          ]
        }
      }
    }
  ],
  "configuration_version": "1"
}
